cwspy/__init__.py
cwspy/api.py
cwspy/data.py
cwspy/errors.py
cwspy/helpers.py
cwspy-0.1.5.dist-info/DESCRIPTION.rst
cwspy-0.1.5.dist-info/METADATA
cwspy-0.1.5.dist-info/RECORD
cwspy-0.1.5.dist-info/WHEEL
cwspy-0.1.5.dist-info/metadata.json
cwspy-0.1.5.dist-info/top_level.txt
