Metadata-Version: 2.0
Name: cwspy
Version: 0.1.5
Summary: A simple API wrapper for ConWorkShop
Home-page: UNKNOWN
Author: xylophonw
Author-email: diatelephone@gmail.com
License: MIT
Keywords: api development conlang conlanging
Platform: UNKNOWN
Classifier: Development Status :: 3 - Alpha
Classifier: Intended Audience :: Developers
Classifier: Topic :: Software Development :: Libraries
Classifier: License :: OSI Approved :: MIT License
Classifier: Programming Language :: Python :: 3.6
